mosaik.EId-0.1.0rc20221002000538-py3.8-nspkg.pth
mosaik_eid/eid/__init__.py
mosaik_eid/eid/eid_manager.py
mosaik_eid/eid/eid_parser.py
mosaik_eid/eid/entity_exception.py
mosaik_eid/eid/entity_identifier.py
mosaik_eid/eid/entity_type.py
mosaik_eid/eid/entity_type_registry.py
mosaik.EId-0.1.0rc20221002000538.dist-info/LICENSE.txt
mosaik.EId-0.1.0rc20221002000538.dist-info/METADATA
mosaik.EId-0.1.0rc20221002000538.dist-info/WHEEL
mosaik.EId-0.1.0rc20221002000538.dist-info/entry_points.txt
mosaik.EId-0.1.0rc20221002000538.dist-info/namespace_packages.txt
mosaik.EId-0.1.0rc20221002000538.dist-info/top_level.txt
mosaik.EId-0.1.0rc20221002000538.dist-info/RECORD
